positivitypy/__init__.py
positivitypy/predict.py
positivitypy-1.1.0.dist-info/METADATA
positivitypy-1.1.0.dist-info/WHEEL
positivitypy-1.1.0.dist-info/top_level.txt
positivitypy-1.1.0.dist-info/RECORD
