Metadata-Version: 2.1
Name: positivitypy
Version: 1.1.0
Summary: Detecting if text is in positive or negative sense. Can be used to classify reviews.
Home-page: UNKNOWN
Author: sudip-mondal-2002 (Sudip Mondal)
Author-email: <sudipmondal.2002@rediffmail.com>
License: UNKNOWN
Keywords: python,NLP,machine-learning,review,classification
Platform: UNKNOWN
Classifier: Programming Language :: Python :: 3
Classifier: Operating System :: Unix
Classifier: Operating System :: MacOS :: MacOS X
Classifier: Operating System :: Microsoft :: Windows
Requires-Dist: opencv-python
Requires-Dist: pyautogui
Requires-Dist: pyaudio
